odoo10_addon_board_frontdesk-10.0.1.0.0.99.dev13-py2.7-nspkg.pth
odoo/addons/board_frontdesk/README.rst
odoo/addons/board_frontdesk/__init__.py
odoo/addons/board_frontdesk/__manifest__.py
odoo/addons/board_frontdesk/Doc/ChangeLog.txt
odoo/addons/board_frontdesk/LICENSE/LICENSE
odoo/addons/board_frontdesk/i18n/es.po
odoo/addons/board_frontdesk/i18n/fi.po
odoo/addons/board_frontdesk/i18n/fr_BE.po
odoo/addons/board_frontdesk/i18n/sv.po
odoo/addons/board_frontdesk/static/description/currency.png
odoo/addons/board_frontdesk/static/description/icon.png
odoo/addons/board_frontdesk/static/description/quickreservation.png
odoo/addons/board_frontdesk/static/description/reservation.png
odoo/addons/board_frontdesk/static/description/romres.png
odoo/addons/board_frontdesk/static/description/roomdetails.png
odoo/addons/board_frontdesk/static/description/serpent.png
odoo/addons/board_frontdesk/static/description/todayorder.png
odoo/addons/board_frontdesk/views/board_frontdesk_view.xml
odoo10_addon_board_frontdesk-10.0.1.0.0.99.dev13.dist-info/DESCRIPTION.rst
odoo10_addon_board_frontdesk-10.0.1.0.0.99.dev13.dist-info/METADATA
odoo10_addon_board_frontdesk-10.0.1.0.0.99.dev13.dist-info/RECORD
odoo10_addon_board_frontdesk-10.0.1.0.0.99.dev13.dist-info/WHEEL
odoo10_addon_board_frontdesk-10.0.1.0.0.99.dev13.dist-info/metadata.json
odoo10_addon_board_frontdesk-10.0.1.0.0.99.dev13.dist-info/namespace_packages.txt
odoo10_addon_board_frontdesk-10.0.1.0.0.99.dev13.dist-info/top_level.txt
