Metadata-Version: 2.0
Name: odoo10-addon-board-frontdesk
Version: 10.0.1.0.0.99.dev13
Summary: Board for Hotel FrontDesk
Home-page: http://www.serpentcs.com
Author: Odoo Community Association (OCA), Serpent Consulting                Services Pvt. Ltd., ODOO S.A.
Author-email: support@odoo-community.org
License: AGPL-3
Platform: UNKNOWN
Classifier: Programming Language :: Python
Classifier: Framework :: Odoo
Classifier: License :: OSI Approved :: GNU Affero General Public License v3
Requires-Python: ~=2.7
Requires-Dist: odoo (<10.1dev,>=10.0)
Requires-Dist: odoo10-addon-report-hotel-reservation
Requires-Dist: odoo10-addon-report-hotel-restaurant
